{
	"credit": "Created by Stridey, modified by Zecryt",
	"ambientocclusion": false,
	"texture_size": [32, 32],
	"textures": {
		"particle": "#texture"
	},
	"elements": [
		{
			"from": [-4, 0, 8],
			"to": [20, 32, 8],
			"shade": false,
			"rotation": {"angle": 45, "axis": "y", "origin": [8, 8, 8], "rescale": true},
			"faces": {
				"north": {"uv": [0, 0, 16, 16], "texture": "#texture"},
				"south": {"uv": [0, 0, 16, 16], "texture": "#texture"}
			}
		},
		{
			"from": [8, 0, -4],
			"to": [8, 32, 20],
			"shade": false,
			"rotation": {"angle": 45, "axis": "y", "origin": [8, 16, 8], "rescale": true},
			"faces": {
				"east": {"uv": [0, 0, 16, 16], "texture": "#texture"},
				"west": {"uv": [0, 0, 16, 16], "texture": "#texture"}
			}
		},
		{
			"from": [9, 15, -4],
			"to": [9, 31, 20],
			"shade": false,
			"rotation": {"angle": -22.5, "axis": "z", "origin": [9, 31, 8], "rescale": true},
			"faces": {
				"east": {"uv": [2, 0, 14, 8], "texture": "#texture"},
				"west": {"uv": [2, 0, 14, 8], "texture": "#texture"}
			}
		},
		{
			"from": [7, 15, -4],
			"to": [7, 31, 20],
			"shade": false,
			"rotation": {"angle": 22.5, "axis": "z", "origin": [7, 31, 8], "rescale": true},
			"faces": {
				"east": {"uv": [14, 0, 2, 8], "texture": "#texture"},
				"west": {"uv": [14, 0, 2, 8], "texture": "#texture"}
			}
		},
		{
			"from": [-4, 15, 9],
			"to": [20, 31, 9],
			"shade": false,
			"rotation": {"angle": 22.5, "axis": "x", "origin": [8, 31, 9], "rescale": true},
			"faces": {
				"north": {"uv": [2, 0, 14, 8], "texture": "#texture"},
				"south": {"uv": [2, 0, 14, 8], "texture": "#texture"}
			}
		},
		{
			"from": [-4, 15, 7],
			"to": [20, 31, 7],
			"shade": false,
			"rotation": {"angle": -22.5, "axis": "x", "origin": [8, 31, 7], "rescale": true},
			"faces": {
				"north": {"uv": [14, 0, 2, 8], "texture": "#texture"},
				"south": {"uv": [14, 0, 2, 8], "texture": "#texture"}
			}
		}
	],
	"groups": [
		0,
		1,
		{
			"name": "X",
			"origin": [8, 15, 8],
			"color": 0,
			"children": [2, 3]
		},
		{
			"name": "Z",
			"origin": [8, 15, 8],
			"color": 0,
			"children": [4, 5]
		}
	]
}